duckdb_extensions/__init__.py
duckdb_extensions/extension_importer.py
duckdb_extensions-1.4.3.dist-info/METADATA
duckdb_extensions-1.4.3.dist-info/WHEEL
duckdb_extensions-1.4.3.dist-info/licenses/LICENSE.md
duckdb_extensions-1.4.3.dist-info/RECORD
